audit_log/__init__.py
audit_log/exceptions.py
audit_log/headers.py
audit_log/log.py
audit_log/py.typed
audit_log/schema.py
iceye_audit_log-0.2.1.dist-info/licenses/LICENSE
iceye_audit_log-0.2.1.dist-info/METADATA
iceye_audit_log-0.2.1.dist-info/WHEEL
iceye_audit_log-0.2.1.dist-info/top_level.txt
iceye_audit_log-0.2.1.dist-info/RECORD
