Metadata-Version: 2.4
Name: iceye-audit-log
Version: 0.2.1
Summary: Audit logging library for Python
License: MIT License
Project-URL: repository, https://github.com/iceye-ltd/python-audit-log
Classifier: Development Status :: 3 - Alpha
Classifier: License :: OSI Approved :: MIT License
Classifier: Operating System :: OS Independent
Classifier: Programming Language :: Python :: 3.11
Classifier: Programming Language :: Python :: 3.12
Classifier: Programming Language :: Python :: 3.13
Classifier: Programming Language :: Python :: 3.14
Classifier: Programming Language :: Python :: 3
Classifier: Topic :: System :: Logging
Requires-Python: >=3.11
License-File: LICENSE
Dynamic: license-file
